{
    "exercises": [
      {
        "day": "1",
        "exercise_list": [
          {"name":"Lunge OR Squat","code":"66","sets":"3","reps":"", "feedback":"2", "video_link":"https://www.youtube.com/watch?v=IODxDxX7oi4"},
          {"name":"Lunge OR Squat","code":"66","sets":"3","reps":"", "feedback":"2", "video_link":"https://www.youtube.com/watch?v=IODxDxX7oi4"},
          {"name":"Glutes Or Leg failure","code":"70","sets":"3","reps":"", "feedback":"3", "video_link":"https://www.youtube.com/watch?v=IODxDxX7oi4"},
          {"name":"Conditioning plyometric lower","code":"62","sets":"3","reps":"", "feedback":"4", "video_link":"https://www.youtube.com/watch?v=IODxDxX7oi4"},
          {"name":"Conditioning plyometric lower","code":"62","sets":"3","reps":"", "feedback":"4", "video_link":"https://www.youtube.com/watch?v=IODxDxX7oi4"},
          {"name":"Conditioning lower exercises","code":"68","sets":"3","reps":"", "feedback":"5", "video_link":"https://www.youtube.com/watch?v=IODxDxX7oi4"},
          {"name":"Abdominals Isokinetic (till failure)","code":"61","sets":"3","reps":"till failure", "feedback":"3", "video_link":"https://www.youtube.com/watch?v=IODxDxX7oi4"}
        ]
      }, {
        "day": "2",
        "exercise_list": [
            {"name":"Push up variations","code":"67","sets":"3","reps":"", "feedback":"3", "video_link":"https://www.youtube.com/watch?v=IODxDxX7oi4"},
            {"name":"Upper failure exercises pull","code":"59","sets":"3","reps":"", "feedback":"2", "video_link":"https://www.youtube.com/watch?v=IODxDxX7oi4"},
            {"name":"Conditioning upper exercises","code":"69","sets":"3","reps":"", "feedback":"4", "video_link":"https://www.youtube.com/watch?v=IODxDxX7oi4"},
            {"name":"Conditioning upper exercises","code":"69","sets":"3","reps":"", "feedback":"2", "video_link":"https://www.youtube.com/watch?v=IODxDxX7oi4"},
            {"name":"Conditioning upper exercises","code":"69","sets":"3","reps":"", "feedback":"5", "video_link":"https://www.youtube.com/watch?v=IODxDxX7oi4"},
            {"name":"Abdominals Isometric","code":"60","sets":"3","reps":"", "feedback":"3", "video_link":"https://www.youtube.com/watch?v=IODxDxX7oi4"}
          ]
      }, {
        "day": "3",
        "exercise_list": [
          {"name":"Lunge OR Squat","code":"66","sets":"3","reps":"", "feedback":"4", "video_link":"https://www.youtube.com/watch?v=IODxDxX7oi4"},
          {"name":"Lunge OR Squat","code":"66","sets":"3","reps":"", "feedback":"3", "video_link":"https://www.youtube.com/watch?v=IODxDxX7oi4"},
          {"name":"Glutes Or Leg failure","code":"70","sets":"3","reps":"", "feedback":"4", "video_link":"https://www.youtube.com/watch?v=IODxDxX7oi4"},
          {"name":"Conditioning plyometric lower","code":"62","sets":"3","reps":"", "feedback":"3", "video_link":"https://www.youtube.com/watch?v=IODxDxX7oi4"},
          {"name":"Conditioning plyometric lower","code":"62","sets":"3","reps":"", "feedback":"2", "video_link":"https://www.youtube.com/watch?v=IODxDxX7oi4"},
          {"name":"Conditioning lower exercises","code":"68","sets":"3","reps":"", "feedback":"2", "video_link":"https://www.youtube.com/watch?v=IODxDxX7oi4"},
          {"name":"Abdominals Isokinetic (till failure)","code":"61","sets":"3","reps":"", "feedback":"5", "video_link":"https://www.youtube.com/watch?v=IODxDxX7oi4"}
        ]
      }
    ]
  }
  