{
  "_class": "shapeGroup",
  "clippingMaskMode": 0,
  "do_objectID": "B39E1F4F-551E-4002-B2D4-08B212B811CD",
  "exportOptions": {
    "_class": "exportOptions",
    "exportFormats": [
    ],
    "includedLayerIds": [
    ],
    "layerOptions": 0,
    "shouldTrim": false
  },
  "frame": {
    "_class": "rect",
    "constrainProportions": false,
    "height": 582,
    "width": 750.0000000000001,
    "x": 0,
    "y": 4.547473508864641e-13
  },
  "hasClickThrough": false,
  "hasClippingMask": false,
  "isFlippedHorizontal": false,
  "isFlippedVertical": false,
  "isLocked": false,
  "isVisible": true,
  "layerListExpandedType": 0,
  "layers": [
    {
      "class": "rectangle",
      "id": "D5B57078-2391-4D3D-8363-58AD2536E3F8"
    }
  ],
  "name": "Modal Overlay Copy 3",
  "nameIsFixed": false,
  "originalObjectID": "F10C3721-615E-40B0-B65D-D8FE7E1AA8F1",
  "resizingConstraint": 63,
  "resizingType": 0,
  "rotation": 0,
  "shouldBreakMaskChain": false,
  "style": {
    "sharedObjectID": "1596CEFF-BC53-4A5C-BEA3-E79C3C0D2CDA"
  },
  "windingRule": 1
}