{
  "_class": "shapePath",
  "booleanOperation": -1,
  "do_objectID": "629CDF60-EDB2-4E5D-BB7D-5AD198A26E85",
  "edited": true,
  "exportOptions": {
    "_class": "exportOptions",
    "exportFormats": [
    ],
    "includedLayerIds": [
    ],
    "layerOptions": 0,
    "shouldTrim": false
  },
  "frame": {
    "_class": "rect",
    "constrainProportions": false,
    "height": 38.79614237288136,
    "width": 38.79614237288137,
    "x": 0,
    "y": 0
  },
  "isFlippedHorizontal": false,
  "isFlippedVertical": false,
  "isLocked": false,
  "isVisible": true,
  "layerListExpandedType": 0,
  "name": "Path",
  "nameIsFixed": false,
  "path": {
    "_class": "path",
    "isClosed": true,
    "points": [
      {
        "_class": "curvePoint",
        "cornerRadius": 0,
        "curveFrom": "{0, 1}",
        "curveMode": 1,
        "curveTo": "{0, 1}",
        "hasCurveFrom": false,
        "hasCurveTo": false,
        "point": "{0, 1}"
      },
      {
        "_class": "curvePoint",
        "cornerRadius": 0,
        "curveFrom": "{1, 1}",
        "curveMode": 1,
        "curveTo": "{1, 1}",
        "hasCurveFrom": false,
        "hasCurveTo": false,
        "point": "{1, 1}"
      },
      {
        "_class": "curvePoint",
        "cornerRadius": 0,
        "curveFrom": "{1, 0}",
        "curveMode": 1,
        "curveTo": "{1, 0}",
        "hasCurveFrom": false,
        "hasCurveTo": false,
        "point": "{1, 0}"
      },
      {
        "_class": "curvePoint",
        "cornerRadius": 0,
        "curveFrom": "{3.0788113133892652e-22, 0}",
        "curveMode": 1,
        "curveTo": "{3.0788113133892652e-22, 0}",
        "hasCurveFrom": false,
        "hasCurveTo": false,
        "point": "{3.0788113133892652e-22, 0}"
      },
      {
        "_class": "curvePoint",
        "cornerRadius": 0,
        "curveFrom": "{3.0788113133892652e-22, 1}",
        "curveMode": 1,
        "curveTo": "{3.0788113133892652e-22, 1}",
        "hasCurveFrom": false,
        "hasCurveTo": false,
        "point": "{3.0788113133892652e-22, 1}"
      }
    ]
  },
  "resizingType": 0,
  "rotation": 0,
  "shouldBreakMaskChain": false
}