{
  "_class": "shapeGroup",
  "clippingMaskMode": 0,
  "do_objectID": "F9911418-3F33-402D-B1D1-FFF7F4F0CEB8",
  "exportOptions": {
    "_class": "exportOptions",
    "exportFormats": [
    ],
    "includedLayerIds": [
    ],
    "layerOptions": 0,
    "shouldTrim": false
  },
  "frame": {
    "_class": "rect",
    "constrainProportions": false,
    "height": 19.69370917727453,
    "width": 45.16051896064297,
    "x": 690.4612907298597,
    "y": 9.695717455517297
  },
  "hasClickThrough": false,
  "hasClippingMask": false,
  "isFlippedHorizontal": false,
  "isFlippedVertical": false,
  "isLocked": false,
  "isVisible": true,
  "layerListExpandedType": 1,
  "layers": [
    {
      "class": "shapePath",
      "id": "C01D2F5C-9D8C-488A-A381-23C37589EC9E"
    },
    {
      "class": "shapePath",
      "id": "80321421-E178-4D88-8A27-DD85E16A7EE4"
    }
  ],
  "name": "Shape",
  "nameIsFixed": false,
  "originalObjectID": "757CE90A-FC69-48D8-B7FE-B46F187FC41A",
  "resizingConstraint": 63,
  "resizingType": 0,
  "rotation": 0,
  "shouldBreakMaskChain": false,
  "style": {
    "_class": "style",
    "blur": {
      "_class": "blur",
      "center": "{0.5, 0.5}",
      "isEnabled": false,
      "motionAngle": 0,
      "radius": 5,
      "type": 0
    },
    "endDecorationType": 0,
    "fills": [
      {
        "_class": "fill",
        "color": {
          "_class": "color",
          "alpha": 1,
          "blue": 1,
          "green": 1,
          "red": 1
        },
        "fillType": 0,
        "isEnabled": true,
        "noiseIndex": 0,
        "noiseIntensity": 0,
        "patternFillType": 0,
        "patternTileScale": 1
      }
    ],
    "miterLimit": 10,
    "startDecorationType": 0
  },
  "windingRule": 0
}